[
    {
        "id": "11317530",
        "name": "I-Dle – Girlfriend",
        "url": "https:\/\/dl1.mp3party.net\/online\/11317530.mp3",
        "time": "02:42"
    },
    {
        "id": "11317576",
        "name": "ROSÉ – Messy",
        "url": "https:\/\/dl1.mp3party.net\/online\/11317576.mp3",
        "time": "02:59"
    },
    {
        "id": "11315618",
        "name": "Паша Proorok, KalashnikoFF – Песня про лето",
        "url": "https:\/\/dl1.mp3party.net\/online\/11315618.mp3",
        "time": "03:09"
    },
    {
        "id": "11315997",
        "name": "BABYMONSTER – Ghost",
        "url": "https:\/\/dl1.mp3party.net\/online\/11315997.mp3",
        "time": "03:02"
    },
    {
        "id": "11315609",
        "name": "3-ий Январь – Самая родная",
        "url": "https:\/\/dl1.mp3party.net\/online\/11315609.mp3",
        "time": "02:30"
    },
    {
        "id": "11316011",
        "name": "Лисицын – Ладонь",
        "url": "https:\/\/dl1.mp3party.net\/online\/11316011.mp3",
        "time": "03:53"
    },
    {
        "id": "11315626",
        "name": "ARXF, Sayfalse – TOMA ALTURA",
        "url": "https:\/\/dl1.mp3party.net\/online\/11315626.mp3",
        "time": "01:25"
    },
    {
        "id": "11316984",
        "name": "★ 9 Мая – Журавли",
        "url": "https:\/\/dl1.mp3party.net\/online\/11316984.mp3",
        "time": "04:07"
    },
    {
        "id": "11316988",
        "name": "Левитан – День Победы",
        "url": "https:\/\/dl1.mp3party.net\/online\/11316988.mp3",
        "time": "04:08"
    },
    {
        "id": "11316986",
        "name": "9 МАЯ – Вставай страна огромная",
        "url": "https:\/\/dl1.mp3party.net\/online\/11316986.mp3",
        "time": "03:28"
    },
    {
        "id": "11315625",
        "name": "LXNGVX, Maestro Chives – Royalty Funk",
        "url": "https:\/\/dl1.mp3party.net\/online\/11315625.mp3",
        "time": "02:57"
    },
    {
        "id": "11317855",
        "name": "Three Days Grace – Apologies",
        "url": "https:\/\/dl1.mp3party.net\/online\/11317855.mp3",
        "time": "03:06"
    },
    {
        "id": "11316981",
        "name": "9 МАЯ – Смуглянка",
        "url": "https:\/\/dl1.mp3party.net\/online\/11316981.mp3",
        "time": "03:28"
    },
    {
        "id": "11316982",
        "name": "9 МАЯ – Идет солдат по городу",
        "url": "https:\/\/dl1.mp3party.net\/online\/11316982.mp3",
        "time": "03:13"
    },
    {
        "id": "11315624",
        "name": "Proof nation – BECO DA FAVELA",
        "url": "https:\/\/dl1.mp3party.net\/online\/11315624.mp3",
        "time": "01:24"
    },
    {
        "id": "11316985",
        "name": "9 МАЯ – День Победы",
        "url": "https:\/\/dl1.mp3party.net\/online\/11316985.mp3",
        "time": "03:17"
    },
    {
        "id": "11317629",
        "name": "P1harmony – Pretty Boy",
        "url": "https:\/\/dl1.mp3party.net\/online\/11317629.mp3",
        "time": "02:57"
    },
    {
        "id": "11317625",
        "name": "P1harmony – DUH!",
        "url": "https:\/\/dl1.mp3party.net\/online\/11317625.mp3",
        "time": "03:05"
    },
    {
        "id": "11317666",
        "name": "Avril Lavigne – Young & Dumb (feat. Simple Plan)",
        "url": "https:\/\/dl1.mp3party.net\/online\/11317666.mp3",
        "time": "02:46"
    },
    {
        "id": "11315952",
        "name": "Sleep Token – Provider",
        "url": "https:\/\/dl1.mp3party.net\/online\/11315952.mp3",
        "time": "06:05"
    },
    {
        "id": "11315958",
        "name": "Sleep Token – Dangerous",
        "url": "https:\/\/dl1.mp3party.net\/online\/11315958.mp3",
        "time": "04:11"
    },
    {
        "id": "11316960",
        "name": "Maxim Zavidia – Ты весна",
        "url": "https:\/\/dl1.mp3party.net\/online\/11316960.mp3",
        "time": "02:27"
    },
    {
        "id": "11315954",
        "name": "Sleep Token – Look to Windward",
        "url": "https:\/\/dl1.mp3party.net\/online\/11315954.mp3",
        "time": "07:46"
    },
    {
        "id": "11316012",
        "name": "T1One – Однажды",
        "url": "https:\/\/dl1.mp3party.net\/online\/11316012.mp3",
        "time": "02:39"
    },
    {
        "id": "11315725",
        "name": "XTENTACION – MOONLIGHT",
        "url": "https:\/\/dl1.mp3party.net\/online\/11315725.mp3",
        "time": "03:39"
    },
    {
        "id": "11316950",
        "name": "Dj Polkovnik, N-ASTI – Casablanca",
        "url": "https:\/\/dl1.mp3party.net\/online\/11316950.mp3",
        "time": "02:33"
    },
    {
        "id": "11315957",
        "name": "Sleep Token – Even in Arcadia",
        "url": "https:\/\/dl1.mp3party.net\/online\/11315957.mp3",
        "time": "04:28"
    },
    {
        "id": "11315956",
        "name": "Sleep Token – Gethsemane",
        "url": "https:\/\/dl1.mp3party.net\/online\/11315956.mp3",
        "time": "06:23"
    },
    {
        "id": "11317025",
        "name": "Halsey – Hand That Feeds (feat. Amy Lee, Evanescence)",
        "url": "https:\/\/dl1.mp3party.net\/online\/11317025.mp3",
        "time": "03:06"
    },
    {
        "id": "11316983",
        "name": "9 МАЯ – Синий платочек",
        "url": "https:\/\/dl1.mp3party.net\/online\/11316983.mp3",
        "time": "02:33"
    },
    {
        "id": "11315953",
        "name": "Sleep Token – Past Self",
        "url": "https:\/\/dl1.mp3party.net\/online\/11315953.mp3",
        "time": "03:34"
    },
    {
        "id": "11315955",
        "name": "Sleep Token – Infinite Baths",
        "url": "https:\/\/dl1.mp3party.net\/online\/11315955.mp3",
        "time": "08:23"
    },
    {
        "id": "11316987",
        "name": "Дорин Виктор – За Победу",
        "url": "https:\/\/dl1.mp3party.net\/online\/11316987.mp3",
        "time": "03:36"
    },
    {
        "id": "11315951",
        "name": "Jahmal TGK – Чёрно-белый Танкоград (Melody $hit Baile Edit)",
        "url": "https:\/\/dl1.mp3party.net\/online\/11315951.mp3",
        "time": "02:53"
    },
    {
        "id": "11317089",
        "name": "Calvin Harris – Blessings (feat. Clementine Douglas)",
        "url": "https:\/\/dl1.mp3party.net\/online\/11317089.mp3",
        "time": "03:39"
    },
    {
        "id": "11315544",
        "name": "Parkway Drive – Sacred",
        "url": "https:\/\/dl1.mp3party.net\/online\/11315544.mp3",
        "time": "03:49"
    },
    {
        "id": "11315622",
        "name": "Bahh Tee – Знает лишь июль",
        "url": "https:\/\/dl1.mp3party.net\/online\/11315622.mp3",
        "time": "03:10"
    },
    {
        "id": "11316503",
        "name": "2Pac – Other Position (feat. Miyagi. DarK Boy Remix)",
        "url": "https:\/\/dl1.mp3party.net\/online\/11316503.mp3",
        "time": "06:02"
    },
    {
        "id": "11315621",
        "name": "Niti dila – Журавли",
        "url": "https:\/\/dl1.mp3party.net\/online\/11315621.mp3",
        "time": "03:11"
    },
    {
        "id": "11315620",
        "name": "Тайпан, Logmarin – Где-то далеко",
        "url": "https:\/\/dl1.mp3party.net\/online\/11315620.mp3",
        "time": "02:37"
    },
    {
        "id": "11315623",
        "name": "HammAli – Живу в первый раз",
        "url": "https:\/\/dl1.mp3party.net\/online\/11315623.mp3",
        "time": "03:58"
    },
    {
        "id": "11317022",
        "name": "Женя Белоусов – Девчонка-девчоночка (DJ Smell Remix)",
        "url": "https:\/\/dl1.mp3party.net\/online\/11317022.mp3",
        "time": "02:30"
    },
    {
        "id": "11315579",
        "name": "RAIZHELL – PULL THE TRIGGER (Dubstep Remix)",
        "url": "https:\/\/dl1.mp3party.net\/online\/11315579.mp3",
        "time": "03:07"
    },
    {
        "id": "11317466",
        "name": "STAVR – Вертоворот",
        "url": "https:\/\/dl1.mp3party.net\/online\/11317466.mp3",
        "time": "01:37"
    },
    {
        "id": "11316972",
        "name": "Юрий Гуляев, Юрий Силантьев, – На безымянной высоте",
        "url": "https:\/\/dl1.mp3party.net\/online\/11316972.mp3",
        "time": "04:34"
    },
    {
        "id": "11315607",
        "name": "Citizen Soldier – Inner Critic",
        "url": "https:\/\/dl1.mp3party.net\/online\/11315607.mp3",
        "time": "03:24"
    },
    {
        "id": "11315729",
        "name": "Khaled – Aicha (KaktuZ Remix)",
        "url": "https:\/\/dl1.mp3party.net\/online\/11315729.mp3",
        "time": "03:38"
    },
    {
        "id": "11315976",
        "name": "Kylie Cantrall, ILLIT – See U Tonight (feat. YUNAH & MINJU of ILLIT)",
        "url": "https:\/\/dl1.mp3party.net\/online\/11315976.mp3",
        "time": "02:10"
    },
    {
        "id": "11316971",
        "name": "Ярослав Евдокимов – Майский вальс",
        "url": "https:\/\/dl1.mp3party.net\/online\/11316971.mp3",
        "time": "03:40"
    },
    {
        "id": "11317630",
        "name": "P1harmony – Work",
        "url": "https:\/\/dl1.mp3party.net\/online\/11317630.mp3",
        "time": "03:32"
    },
    {
        "id": "11316970",
        "name": "Марк Рейзен – Эх, дороги",
        "url": "https:\/\/dl1.mp3party.net\/online\/11316970.mp3",
        "time": "03:54"
    },
    {
        "id": "11315728",
        "name": "Freddie Mercury – Living On My Own (Dario Caminita Remix)",
        "url": "https:\/\/dl1.mp3party.net\/online\/11315728.mp3",
        "time": "05:00"
    },
    {
        "id": "11317021",
        "name": "Armin van Buuren – Bach To The Future (feat. BLR)",
        "url": "https:\/\/dl1.mp3party.net\/online\/11317021.mp3",
        "time": "03:29"
    },
    {
        "id": "11317919",
        "name": "Камаз – Не оставляй меня",
        "url": "https:\/\/dl1.mp3party.net\/online\/11317919.mp3",
        "time": "03:45"
    },
    {
        "id": "11317942",
        "name": "Savage – Goodbye (Andrea Cecchini, Luka J Master, Steve Martin Remix)",
        "url": "https:\/\/dl1.mp3party.net\/online\/11317942.mp3",
        "time": "04:06"
    },
    {
        "id": "11317627",
        "name": "P1harmony – Murmur",
        "url": "https:\/\/dl1.mp3party.net\/online\/11317627.mp3",
        "time": "03:09"
    },
    {
        "id": "11317628",
        "name": "P1harmony – Over And Over",
        "url": "https:\/\/dl1.mp3party.net\/online\/11317628.mp3",
        "time": "02:54"
    },
    {
        "id": "11317940",
        "name": "Fancy – Slice Me Nice (Brave 2025 Remix)",
        "url": "https:\/\/dl1.mp3party.net\/online\/11317940.mp3",
        "time": "03:09"
    },
    {
        "id": "11316976",
        "name": "Игорь Слуцкий – За Победу !!!",
        "url": "https:\/\/dl1.mp3party.net\/online\/11316976.mp3",
        "time": "03:39"
    },
    {
        "id": "11316335",
        "name": "The Pretty Wild – Omens",
        "url": "https:\/\/dl1.mp3party.net\/online\/11316335.mp3",
        "time": "03:25"
    },
    {
        "id": "11317626",
        "name": "P1harmony – Flashy",
        "url": "https:\/\/dl1.mp3party.net\/online\/11317626.mp3",
        "time": "03:09"
    },
    {
        "id": "11316134",
        "name": "Battle Beast – Last Goodbye",
        "url": "https:\/\/dl1.mp3party.net\/online\/11316134.mp3",
        "time": "03:32"
    },
    {
        "id": "11317871",
        "name": "ЛЮБЭ, Санчес, Yopt – Солдат",
        "url": "https:\/\/dl1.mp3party.net\/online\/11317871.mp3",
        "time": "04:06"
    },
    {
        "id": "11316964",
        "name": "Василий Лановой – Бери шинель, пошли домой",
        "url": "https:\/\/dl1.mp3party.net\/online\/11316964.mp3",
        "time": "04:54"
    },
    {
        "id": "11318890",
        "name": "Юрий Шатунов – Розовый вечер (Index-1 Remix)",
        "url": "https:\/\/dl1.mp3party.net\/online\/11318890.mp3",
        "time": "03:40"
    },
    {
        "id": "11317943",
        "name": "Scatman John – Scatman (Madmind Remix)",
        "url": "https:\/\/dl1.mp3party.net\/online\/11317943.mp3",
        "time": "04:43"
    },
    {
        "id": "11317695",
        "name": "Dead by April – Naked",
        "url": "https:\/\/dl1.mp3party.net\/online\/11317695.mp3",
        "time": "03:43"
    },
    {
        "id": "11316955",
        "name": "Barlas & Mert – Hotel Lobby",
        "url": "https:\/\/dl1.mp3party.net\/online\/11316955.mp3",
        "time": "03:04"
    },
    {
        "id": "11316959",
        "name": "3EL3 – Risen From The Ashes",
        "url": "https:\/\/dl1.mp3party.net\/online\/11316959.mp3",
        "time": "02:29"
    },
    {
        "id": "11318892",
        "name": "AsparagusProject – You';re My Love (feat. Alisha Larry)",
        "url": "https:\/\/dl1.mp3party.net\/online\/11318892.mp3",
        "time": "03:36"
    },
    {
        "id": "11316962",
        "name": "Георгий Виноградов, Дважды Краснознамённый ордена Красной Звезды академический ансамбль песни и пляски Советской Армии имени Александра Александрова – Катюша",
        "url": "https:\/\/dl1.mp3party.net\/online\/11316962.mp3",
        "time": "02:20"
    },
    {
        "id": "11316359",
        "name": "Hakim – Ah Ya Albi (Remix)",
        "url": "https:\/\/dl1.mp3party.net\/online\/11316359.mp3",
        "time": "02:13"
    },
    {
        "id": "11315727",
        "name": "MorozI – Жизнь",
        "url": "https:\/\/dl1.mp3party.net\/online\/11315727.mp3",
        "time": "02:55"
    },
    {
        "id": "11315610",
        "name": "Леонид Максименко – Эй, красотка",
        "url": "https:\/\/dl1.mp3party.net\/online\/11315610.mp3",
        "time": "02:50"
    },
    {
        "id": "11316978",
        "name": "В.Соловьев-Седой, А.Фатьянов, – Давно мы дома не были",
        "url": "https:\/\/dl1.mp3party.net\/online\/11316978.mp3",
        "time": "02:30"
    },
    {
        "id": "11316943",
        "name": "Riltim – You Like Me",
        "url": "https:\/\/dl1.mp3party.net\/online\/11316943.mp3",
        "time": "02:42"
    },
    {
        "id": "11316949",
        "name": "Housenick – Get Higher",
        "url": "https:\/\/dl1.mp3party.net\/online\/11316949.mp3",
        "time": "07:05"
    },
    {
        "id": "11317558",
        "name": "Miley Cyrus – More to Lose",
        "url": "https:\/\/dl1.mp3party.net\/online\/11317558.mp3",
        "time": "04:35"
    },
    {
        "id": "11316948",
        "name": "Amir Nazari – Bodyguard",
        "url": "https:\/\/dl1.mp3party.net\/online\/11316948.mp3",
        "time": "05:05"
    },
    {
        "id": "11316973",
        "name": "Ренат Ибрагимов – За того парня",
        "url": "https:\/\/dl1.mp3party.net\/online\/11316973.mp3",
        "time": "03:50"
    },
    {
        "id": "11315578",
        "name": "Skrillex, Flowdan, BEAM & Peekaboo – Hydrate (Virtual Riot Edit)",
        "url": "https:\/\/dl1.mp3party.net\/online\/11315578.mp3",
        "time": "02:08"
    },
    {
        "id": "11316432",
        "name": "Иракли – Так не бывает (Alex Shik Remix)",
        "url": "https:\/\/dl1.mp3party.net\/online\/11316432.mp3",
        "time": "03:30"
    },
    {
        "id": "11316967",
        "name": "Виктор Волик – Бессмертный Полк",
        "url": "https:\/\/dl1.mp3party.net\/online\/11316967.mp3",
        "time": "03:53"
    },
    {
        "id": "11318783",
        "name": "Искусственный интеллект – Розовый вечер",
        "url": "https:\/\/dl1.mp3party.net\/online\/11318783.mp3",
        "time": "03:18"
    },
    {
        "id": "11317019",
        "name": "Killteq – Aicha (feat. D. Hash. DJ Brooklyn Remix)",
        "url": "https:\/\/dl1.mp3party.net\/online\/11317019.mp3",
        "time": "03:19"
    },
    {
        "id": "11316139",
        "name": "F5ve – Sugar Free Venom (feat. Kesha)",
        "url": "https:\/\/dl1.mp3party.net\/online\/11316139.mp3",
        "time": "02:48"
    },
    {
        "id": "11317938",
        "name": "Geo Da Silva – C'est la vie (feat. Canello)",
        "url": "https:\/\/dl1.mp3party.net\/online\/11317938.mp3",
        "time": "03:20"
    },
    {
        "id": "11316977",
        "name": "Гевиксман Виталий – Березовые сны",
        "url": "https:\/\/dl1.mp3party.net\/online\/11316977.mp3",
        "time": "04:26"
    },
    {
        "id": "11318889",
        "name": "Светлана Рерих – Ладошки (Index-1 Remix)",
        "url": "https:\/\/dl1.mp3party.net\/online\/11318889.mp3",
        "time": "03:28"
    },
    {
        "id": "11316957",
        "name": "New'o & HUGE DAMAGE – Update",
        "url": "https:\/\/dl1.mp3party.net\/online\/11316957.mp3",
        "time": "02:05"
    },
    {
        "id": "11316018",
        "name": "DAY6 – Maybe Tomorrow",
        "url": "https:\/\/dl1.mp3party.net\/online\/11316018.mp3",
        "time": "03:44"
    },
    {
        "id": "11315602",
        "name": "Orbit Culture – The Tales of War (1)",
        "url": "https:\/\/dl1.mp3party.net\/online\/11315602.mp3",
        "time": "05:08"
    },
    {
        "id": "11315616",
        "name": "Sayan – Без памяти",
        "url": "https:\/\/dl1.mp3party.net\/online\/11315616.mp3",
        "time": "02:26"
    },
    {
        "id": "11317944",
        "name": "Block & Crown – I Will Survive (feat. Culum Frea. Robbie Rivera Remix)",
        "url": "https:\/\/dl1.mp3party.net\/online\/11317944.mp3",
        "time": "03:15"
    },
    {
        "id": "11316965",
        "name": "Владимир Высоцкий – Все ушли на фронт",
        "url": "https:\/\/dl1.mp3party.net\/online\/11316965.mp3",
        "time": "02:09"
    },
    {
        "id": "11317939",
        "name": "Eiffel 65 – Blue Da Ba Dee (Samuele Sartini, Cire Remix)",
        "url": "https:\/\/dl1.mp3party.net\/online\/11317939.mp3",
        "time": "04:05"
    },
    {
        "id": "11316958",
        "name": "ALVSTOR – Hater Blockers",
        "url": "https:\/\/dl1.mp3party.net\/online\/11316958.mp3",
        "time": "02:21"
    },
    {
        "id": "11316004",
        "name": "NERVO & Plastik Funk ft. Jul – Talk About Us (Jeonghyeon Remix)",
        "url": "https:\/\/dl1.mp3party.net\/online\/11316004.mp3",
        "time": "02:51"
    },
    {
        "id": "11316910",
        "name": "FRXSTBURN – Andromeda",
        "url": "https:\/\/dl1.mp3party.net\/online\/11316910.mp3",
        "time": "03:19"
    },
    {
        "id": "11316961",
        "name": "Anatoly Prod – Комсомолка 2.0",
        "url": "https:\/\/dl1.mp3party.net\/online\/11316961.mp3",
        "time": "03:42"
    }
]